googletranslatepy/__init__.py
googletranslatepy/bin.py
googletranslatepy/translator.py
googletranslatepy/util.py
googletranslatepy/version.json
googletranslate_python-1.0.3.dist-info/METADATA
googletranslate_python-1.0.3.dist-info/WHEEL
googletranslate_python-1.0.3.dist-info/entry_points.txt
googletranslate_python-1.0.3.dist-info/top_level.txt
googletranslate_python-1.0.3.dist-info/RECORD
