Metadata-Version: 2.1
Name: googletranslate-python
Version: 1.0.3
Summary: Google Translate Client with `deep-translator`
Home-page: https://github.com/suqingdong/googletranslatepy
Author: suqingdong
Author-email: suqingdong1114@gmail.com
License: MIT License
Platform: UNKNOWN
Classifier: Development Status :: 5 - Production/Stable
Classifier: Operating System :: OS Independent
Classifier: Intended Audience :: Developers
Classifier: License :: OSI Approved :: MIT License
Classifier: Programming Language :: Python
Classifier: Programming Language :: Python :: 3
Classifier: Programming Language :: Python :: 3.8
Classifier: Programming Language :: Python :: 3.9
Classifier: Topic :: Software Development :: Libraries
Requires-Dist: rich
Requires-Dist: click
Requires-Dist: deep-translator
